daSC2-0.0.5.dev1.dist-info/DESCRIPTION.rst
daSC2-0.0.5.dev1.dist-info/METADATA
daSC2-0.0.5.dev1.dist-info/RECORD
daSC2-0.0.5.dev1.dist-info/WHEEL
daSC2-0.0.5.dev1.dist-info/entry_points.txt
daSC2-0.0.5.dev1.dist-info/metadata.json
daSC2-0.0.5.dev1.dist-info/top_level.txt
dasc2/__init__.py
dasc2/bin/__init__.py
dasc2/bin/filter_replays.py
dasc2/lib/__init__.py
dasc2/lib/replay_filter.py
