Metadata-Version: 2.0
Name: daSC2
Version: 0.0.5.dev1
Summary: Data Analytics Library for StarCraft II
Home-page: https://github.com/davidkuhta/dasc2
Author: David Kuhta
Author-email: davidkuhta@gmail.com
License: Apache License, Version 2.0
Keywords: StarCraft,StarCraft II,StarCraft 2,StarCraft AI,data analytics,SC2Replay
Platform: UNKNOWN
Classifier: Development Status :: 1 - Planning
Classifier: Environment :: Console
Classifier: Intended Audience :: Science/Research
Classifier: License :: OSI Approved :: Apache Software License
Classifier: Operating System :: POSIX :: Linux
Classifier: Operating System :: Microsoft :: Windows
Classifier: Operating System :: MacOS :: MacOS X
Classifier: Programming Language :: Python :: 2.7
Classifier: Programming Language :: Python :: 3.4
Classifier: Topic :: Scientific/Engineering :: Artificial Intelligence
Requires-Dist: future
Requires-Dist: mpyq
Provides-Extra: with-progress-bar
Requires-Dist: tqdm (>=4.19.4); extra == 'with-progress-bar'
